HDDFeature/__init__.py
HDDFeature/discernibleScore.py
HDDFeature/fastFeatureSelectionDS.py
HDDFeature/increDiscernibleScore.py
HDDFeature/increFeaSltDSFilterSam.py
HDDFeature/increFeatureSelectionDS.py
HDDFeature/partition_fold.py
HDDFeature-0.1.0.dist-info/METADATA
HDDFeature-0.1.0.dist-info/WHEEL
HDDFeature-0.1.0.dist-info/top_level.txt
HDDFeature-0.1.0.dist-info/RECORD
